{"title":"Tushy.Riley.Reid.Being.Riley.Chapter.3.mp4","uid":12476871,"size":305806518,"categoryP":"porn","categoryS":"movie_clips","magnet":"?xt=urn:btih:0a85ba18b0384947008d6354de36dfb502b380b0&amp;dn=Tushy.Riley.Reid.Being.Riley.Chapter.3.mp4&amp;tr=udp%3A%2F%2Ftracker.openbittorrent.com%3A80&amp;tr=udp%3A%2F%2Fopen.demonii.com%3A1337&amp;tr=udp%3A%2F%2Ftracker.coppersurfer.tk%3A6969&amp;tr=udp%3A%2F%2Fexodus.desync.com%3A6969","seeders":4,"leechers":1,"uploader":"ethen07","files":3,"time":1442995543,"description":"Tushy.Riley.Reid.Being.Riley.Chapter.3.mp4\n\n:::SCREENS::: &lt;a href=&quot;\nhttp://www.imgclick.me/?v=wzlk.jpg&quot; rel=&quot;nofollow&quot; target=&quot;_NEW&quot;&gt;\nhttp://www.imgclick.me/?v=wzlk.jpg&lt;/a&gt;\n &lt;a href=&quot;\nhttp://www.imgclick.me/?v=ri9ti.jpg&quot; rel=&quot;nofollow&quot; target=&quot;_NEW&quot;&gt;\nhttp://www.imgclick.me/?v=ri9ti.jpg&lt;/a&gt;\n\nFOR MORE CLICK HERE. &lt;a href=&quot;\nhttps://thepiratebay.mn/user/ethen07&quot; rel=&quot;nofollow&quot; target=&quot;_NEW&quot;&gt;\nhttps://thepiratebay.mn/user/ethen07&lt;/a&gt;\n\nIf you like this torrent, please post a comment!\n\nDon't forget to seed!","torrent":{"xt":"urn:btih:0a85ba18b0384947008d6354de36dfb502b380b0","amp;dn":"Tushy.Riley.Reid.Being.Riley.Chapter.3.mp4","amp;tr":["udp%3A%2F%2Ftracker.openbittorrent.com%3A80","udp%3A%2F%2Fopen.demonii.com%3A1337","udp%3A%2F%2Ftracker.coppersurfer.tk%3A6969","udp%3A%2F%2Fexodus.desync.com%3A6969"],"infoHash":"0a85ba18b0384947008d6354de36dfb502b380b0","infoHashBuffer":{"type":"Buffer","data":[10,133,186,24,176,56,73,71,0,141,99,84,222,54,223,181,2,179,128,176]},"announce":[],"urlList":[]}}