{"title":"2015 FIM Enduro World Championship Rd 5 Rovetta- Italy.mp4","uid":12135171,"size":803516335,"categoryP":"video","categoryS":"other","magnet":"?xt=urn:btih:0f8d47adf75e0abd1edb55fa21dd29050ea4afa8&amp;dn=2015+FIM+Enduro+World+Championship+Rd+5+Rovetta-+Italy.mp4&amp;tr=udp%3A%2F%2Ftracker.openbittorrent.com%3A80&amp;tr=udp%3A%2F%2Fopen.demonii.com%3A1337&amp;tr=udp%3A%2F%2Ftracker.coppersurfer.tk%3A6969&amp;tr=udp%3A%2F%2Fexodus.desync.com%3A6969","seeders":3,"leechers":0,"uploader":"Dirtfrog399","files":1,"time":1437161146,"description":".:: RELEASE iNFO ::..                                 \n      FORMAT.............: MP4 H.264\n      AUDiO..............: 128 kbps 48Hz stereo\n      ENCODiNG...........: AAC                          \n      RESOLUTiON.........: 1278x720                          \n      FRAME RATE.........: 49 FPS\n\n\ntwitter  @dirtfrog399","torrent":{"xt":"urn:btih:0f8d47adf75e0abd1edb55fa21dd29050ea4afa8","amp;dn":"2015+FIM+Enduro+World+Championship+Rd+5+Rovetta-+Italy.mp4","amp;tr":["udp%3A%2F%2Ftracker.openbittorrent.com%3A80","udp%3A%2F%2Fopen.demonii.com%3A1337","udp%3A%2F%2Ftracker.coppersurfer.tk%3A6969","udp%3A%2F%2Fexodus.desync.com%3A6969"],"infoHash":"0f8d47adf75e0abd1edb55fa21dd29050ea4afa8","infoHashBuffer":{"type":"Buffer","data":[15,141,71,173,247,94,10,189,30,219,85,250,33,221,41,5,14,164,175,168]},"announce":[],"urlList":[]}}