{"title":"Beauty.and.the.Beast.2009.DVDRip.XviD-M00DY","uid":5302481,"size":748620995,"categoryP":"video","categoryS":"movies","magnet":"?xt=urn:btih:0fc94533bb3aca8ee34d51e2c22ac0a7c396704d&amp;dn=Beauty.and.the.Beast.2009.DVDRip.XviD-M00DY&amp;tr=udp%3A%2F%2Ftracker.openbittorrent.com%3A80&amp;tr=udp%3A%2F%2Fopen.demonii.com%3A1337&amp;tr=udp%3A%2F%2Ftracker.coppersurfer.tk%3A6969&amp;tr=udp%3A%2F%2Fexodus.desync.com%3A6969","seeders":4,"leechers":1,"uploader":".BONE.","files":-1,"time":1264270771,"description":"NFO\n\nRuntime: 1h 48 min\nVideo Xvid 956 kbps\nAudio: MP3 ch 128 kbps\nLanguaje: English\nSubtitles: none\n\nA dark twist on the morality tale of forbidden love between beautiful Belle and the feared forest Beast. As villagers are being brutally murdered and the Beast is hunted down as the one responsible for the mayhem, Belle and Beast team up to defeat the real killer the power-hungry witch's malevolent troll.","torrent":{"xt":"urn:btih:0fc94533bb3aca8ee34d51e2c22ac0a7c396704d","amp;dn":"Beauty.and.the.Beast.2009.DVDRip.XviD-M00DY","amp;tr":["udp%3A%2F%2Ftracker.openbittorrent.com%3A80","udp%3A%2F%2Fopen.demonii.com%3A1337","udp%3A%2F%2Ftracker.coppersurfer.tk%3A6969","udp%3A%2F%2Fexodus.desync.com%3A6969"],"infoHash":"0fc94533bb3aca8ee34d51e2c22ac0a7c396704d","infoHashBuffer":{"type":"Buffer","data":[15,201,69,51,187,58,202,142,227,77,81,226,194,42,192,167,195,150,112,77]},"announce":[],"urlList":[]}}