{"title":"Earth's Children Series Bundle - Jean M. Auel (Retail)","uid":9790416,"size":9953311,"categoryP":"other","categoryS":"e_books","magnet":"?xt=urn:btih:1070a075e864709cfa29466b9a78884be99a7d12&amp;dn=Earth%27s+Children+Series+Bundle+-+Jean+M.+Auel+%28Retail%29&amp;tr=udp%3A%2F%2Ftracker.openbittorrent.com%3A80&amp;tr=udp%3A%2F%2Fopen.demonii.com%3A1337&amp;tr=udp%3A%2F%2Ftracker.coppersurfer.tk%3A6969&amp;tr=udp%3A%2F%2Fexodus.desync.com%3A6969","seeders":4,"leechers":0,"uploader":"TheRose88","files":1,"time":1395239343,"description":"The Earth's Children Series: 6 Book Bundle - Jean M. Auel - Retail (epub)\n\n\nThe Earth's Children Series: 6 Book Bundle:\n\n1. THE CLAN OF THE CAVE BEAR\n2. THE VALLEY OF HORSES\n3. THE MAMMOTH HUNTERS\n4. THE PLAINS OF PASSAGE\n5. THE SHELTERS OF STONE\n6. THE LAND OF PAINTED CAVES\n\nA literary phenomenon, Jean M. Auel's prehistoric odyssey is one of the best-loved sagas of our time. Employing meticulous research and the consummate artistry of a master storyteller, Auel paints a vivid panorama of the dawn of modern humans. Through Ayla, an orphaned girl who grows into a beautiful and courageous young woman, we are swept up in the harsh and beautiful Ice Age world, home to the Clan of the Cave Bear. Now, for the first time, all six novels in the Earth's ChildrenÂ® series are available in one convenient eBook bundle.\n","torrent":{"xt":"urn:btih:1070a075e864709cfa29466b9a78884be99a7d12","amp;dn":"Earth%27s+Children+Series+Bundle+-+Jean+M.+Auel+%28Retail%29","amp;tr":["udp%3A%2F%2Ftracker.openbittorrent.com%3A80","udp%3A%2F%2Fopen.demonii.com%3A1337","udp%3A%2F%2Ftracker.coppersurfer.tk%3A6969","udp%3A%2F%2Fexodus.desync.com%3A6969"],"infoHash":"1070a075e864709cfa29466b9a78884be99a7d12","infoHashBuffer":{"type":"Buffer","data":[16,112,160,117,232,100,112,156,250,41,70,107,154,120,136,75,233,154,125,18]},"announce":[],"urlList":[]}}