{"title":"[AssParade] Rachel Starr, Christy Mack (Pornstar Threesome / 07.","uid":8652528,"size":717827477,"categoryP":"porn","categoryS":"movies","magnet":"?xt=urn:btih:1436b105aaaf5e83520fdd73475a8bc2841d7fee&amp;dn=%5BAssParade%5D+Rachel+Starr%2C+Christy+Mack+%28Pornstar+Threesome+%2F+07.&amp;tr=udp%3A%2F%2Ftracker.openbittorrent.com%3A80&amp;tr=udp%3A%2F%2Fopen.demonii.com%3A1337&amp;tr=udp%3A%2F%2Ftracker.coppersurfer.tk%3A6969&amp;tr=udp%3A%2F%2Fexodus.desync.com%3A6969","seeders":4,"leechers":0,"uploader":"chkm8te","files":2,"time":1373142673,"description":"[AssParade] Rachel Starr, Christy Mack (Pornstar Threesome / 07.06.2013)\n\nScreens: &lt;a href=&quot;\nhttp://xxxhost.me/viewer.php?file=70f19dmvogsjlt85dx97.jpg&quot; rel=&quot;nofollow&quot; target=&quot;_NEW&quot;&gt;\nhttp://xxxhost.me/viewer.php?file=70f19dmvogsjlt85dx97.jpg&lt;/a&gt;\n &lt;a href=&quot;\nhttp://xxxhost.me/viewer.php?file=1cwpwuyddi2cyr9zt3ho.jpg&quot; rel=&quot;nofollow&quot; target=&quot;_NEW&quot;&gt;\nhttp://xxxhost.me/viewer.php?file=1cwpwuyddi2cyr9zt3ho.jpg&lt;/a&gt;","torrent":{"xt":"urn:btih:1436b105aaaf5e83520fdd73475a8bc2841d7fee","amp;dn":"%5BAssParade%5D+Rachel+Starr%2C+Christy+Mack+%28Pornstar+Threesome+%2F+07.","amp;tr":["udp%3A%2F%2Ftracker.openbittorrent.com%3A80","udp%3A%2F%2Fopen.demonii.com%3A1337","udp%3A%2F%2Ftracker.coppersurfer.tk%3A6969","udp%3A%2F%2Fexodus.desync.com%3A6969"],"infoHash":"1436b105aaaf5e83520fdd73475a8bc2841d7fee","infoHashBuffer":{"type":"Buffer","data":[20,54,177,5,170,175,94,131,82,15,221,115,71,90,139,194,132,29,127,238]},"announce":[],"urlList":[]}}