{"title":"Daniel Silva - The Fallen Angel - Epub","uid":8826867,"size":483234,"categoryP":"other","categoryS":"e_books","magnet":"?xt=urn:btih:1f192522893780faa303d4ad77992bab324b882c&amp;dn=Daniel+Silva+-+The+Fallen+Angel+-+Epub&amp;tr=udp%3A%2F%2Ftracker.openbittorrent.com%3A80&amp;tr=udp%3A%2F%2Fopen.demonii.com%3A1337&amp;tr=udp%3A%2F%2Ftracker.coppersurfer.tk%3A6969&amp;tr=udp%3A%2F%2Fexodus.desync.com%3A6969","seeders":4,"leechers":0,"uploader":"book1001","files":1,"time":1376866277,"description":" &lt;a href=&quot;http://www.bookidx.com/b/Daniel-Silva/The-Fallen-Angel-Signed-Edition/9780062191458/&quot; rel=&quot;nofollow&quot; target=&quot;_NEW&quot;&gt;http://www.bookidx.com/b/Daniel-Silva/The-Fallen-Angel-Signed-Edition/9780062191458/&lt;/a&gt;","torrent":{"xt":"urn:btih:1f192522893780faa303d4ad77992bab324b882c","amp;dn":"Daniel+Silva+-+The+Fallen+Angel+-+Epub","amp;tr":["udp%3A%2F%2Ftracker.openbittorrent.com%3A80","udp%3A%2F%2Fopen.demonii.com%3A1337","udp%3A%2F%2Ftracker.coppersurfer.tk%3A6969","udp%3A%2F%2Fexodus.desync.com%3A6969"],"infoHash":"1f192522893780faa303d4ad77992bab324b882c","infoHashBuffer":{"type":"Buffer","data":[31,25,37,34,137,55,128,250,163,3,212,173,119,153,43,171,50,75,136,44]},"announce":[],"urlList":[]}}