{"title":"Entwine Magazine - The Digital Crochet Magazine - April, May, Ju","uid":10909455,"size":54216579,"categoryP":"other","categoryS":"e_books","magnet":"?xt=urn:btih:225a83cbd764694308f83d5e2bec870a2c772b0f&amp;dn=Entwine+Magazine+-+The+Digital+Crochet+Magazine+-+April%2C+May%2C+Ju&amp;tr=udp%3A%2F%2Ftracker.openbittorrent.com%3A80&amp;tr=udp%3A%2F%2Fopen.demonii.com%3A1337&amp;tr=udp%3A%2F%2Ftracker.coppersurfer.tk%3A6969&amp;tr=udp%3A%2F%2Fexodus.desync.com%3A6969","seeders":3,"leechers":1,"uploader":"KnitLady","files":-1,"time":1409259728,"description":"Entwine Magazine - The Digital Crochet Magazine - April, May, June, July 2014","torrent":{"xt":"urn:btih:225a83cbd764694308f83d5e2bec870a2c772b0f","amp;dn":"Entwine+Magazine+-+The+Digital+Crochet+Magazine+-+April%2C+May%2C+Ju","amp;tr":["udp%3A%2F%2Ftracker.openbittorrent.com%3A80","udp%3A%2F%2Fopen.demonii.com%3A1337","udp%3A%2F%2Ftracker.coppersurfer.tk%3A6969","udp%3A%2F%2Fexodus.desync.com%3A6969"],"infoHash":"225a83cbd764694308f83d5e2bec870a2c772b0f","infoHashBuffer":{"type":"Buffer","data":[34,90,131,203,215,100,105,67,8,248,61,94,43,236,135,10,44,119,43,15]},"announce":[],"urlList":[]}}