{"title":"Three Kings (1999)  Xvid   NL subs","uid":6573067,"size":996492170,"categoryP":"video","categoryS":"movies","magnet":"?xt=urn:btih:2595eb1a2d6e5f2c94e18a83ef10873450355433&amp;dn=Three+Kings+%281999%29++Xvid+++NL+subs&amp;tr=udp%3A%2F%2Ftracker.openbittorrent.com%3A80&amp;tr=udp%3A%2F%2Fopen.demonii.com%3A1337&amp;tr=udp%3A%2F%2Ftracker.coppersurfer.tk%3A6969&amp;tr=udp%3A%2F%2Fexodus.desync.com%3A6969","seeders":3,"leechers":1,"uploader":"knakworstje","files":1,"time":1312057107,"description":"Verenigde Staten\nActie / Oorlog\n114 minuten\n\n\ngeregisseerd door David O Russell\nmet George Clooney,Mark Wahlberg en Ice Cube\n\n\nEen groepje Amerikaanse soldaten gaat aan het einde van de golfoorlog op zoek naar goud dat Saddam van Koeweit heeft gestolen. Als ze ontdekken dat de plaatselijke bevolking op het punt staat geexecuteerd te worden vanwege de hulp aan de Amerikanen,besluiten ze hen te helpen.\n\n\nIngebakken NL subs.\n\n\n\n\nHard burned DUTCH subs.","torrent":{"xt":"urn:btih:2595eb1a2d6e5f2c94e18a83ef10873450355433","amp;dn":"Three+Kings+%281999%29++Xvid+++NL+subs","amp;tr":["udp%3A%2F%2Ftracker.openbittorrent.com%3A80","udp%3A%2F%2Fopen.demonii.com%3A1337","udp%3A%2F%2Ftracker.coppersurfer.tk%3A6969","udp%3A%2F%2Fexodus.desync.com%3A6969"],"infoHash":"2595eb1a2d6e5f2c94e18a83ef10873450355433","infoHashBuffer":{"type":"Buffer","data":[37,149,235,26,45,110,95,44,148,225,138,131,239,16,135,52,80,53,84,51]},"announce":[],"urlList":[]}}