{"title":"Brasileirinhas - Bruna Ferraz vs. Fernandinha Fernandez","uid":11797953,"size":133626892,"categoryP":"porn","categoryS":"movie_clips","magnet":"?xt=urn:btih:2d15e040201c56b6f8597391403e8ca8b3e4fedc&amp;dn=Brasileirinhas+-+Bruna+Ferraz+vs.+Fernandinha+Fernandez&amp;tr=udp%3A%2F%2Ftracker.openbittorrent.com%3A80&amp;tr=udp%3A%2F%2Fopen.demonii.com%3A1337&amp;tr=udp%3A%2F%2Ftracker.coppersurfer.tk%3A6969&amp;tr=udp%3A%2F%2Fexodus.desync.com%3A6969","seeders":4,"leechers":0,"uploader":"ThousandPeers","files":1,"time":1428254807,"description":"\nScreens &amp; Info :\n\n----------------------------------\n &lt;a href=&quot;\nhttp://lovechix.com/?p=857790&quot; rel=&quot;nofollow&quot; target=&quot;_NEW&quot;&gt;\nhttp://lovechix.com/?p=857790&lt;/a&gt;\n &lt;a href=&quot;\nhttp://lovechix.com/?p=395988&quot; rel=&quot;nofollow&quot; target=&quot;_NEW&quot;&gt;\nhttp://lovechix.com/?p=395988&lt;/a&gt;\n\n----------------------------------\n\nBrowse my entire collection at:\n &lt;a href=&quot;\nhttps://thepiratebay.se/user/kymatica7/&quot; rel=&quot;nofollow&quot; target=&quot;_NEW&quot;&gt;\nhttps://thepiratebay.se/user/kymatica7/&lt;/a&gt;","torrent":{"xt":"urn:btih:2d15e040201c56b6f8597391403e8ca8b3e4fedc","amp;dn":"Brasileirinhas+-+Bruna+Ferraz+vs.+Fernandinha+Fernandez","amp;tr":["udp%3A%2F%2Ftracker.openbittorrent.com%3A80","udp%3A%2F%2Fopen.demonii.com%3A1337","udp%3A%2F%2Ftracker.coppersurfer.tk%3A6969","udp%3A%2F%2Fexodus.desync.com%3A6969"],"infoHash":"2d15e040201c56b6f8597391403e8ca8b3e4fedc","infoHashBuffer":{"type":"Buffer","data":[45,21,224,64,32,28,86,182,248,89,115,145,64,62,140,168,179,228,254,220]},"announce":[],"urlList":[]}}