{"title":"Dada COMPLETE? Discography","uid":4006159,"size":730957005,"categoryP":"audio","categoryS":"music","magnet":"?xt=urn:btih:36815060da5cbbd9059ae34441ac98f6162a1a3e&amp;dn=Dada+COMPLETE%3F+Discography&amp;tr=udp%3A%2F%2Ftracker.openbittorrent.com%3A80&amp;tr=udp%3A%2F%2Fopen.demonii.com%3A1337&amp;tr=udp%3A%2F%2Ftracker.coppersurfer.tk%3A6969&amp;tr=udp%3A%2F%2Fexodus.desync.com%3A6969","seeders":3,"leechers":2,"uploader":"eggshenlps","files":90,"time":1201834405,"description":"Whats up? I decided it was my time to give a little back to the community so here it is my first \ntorrent. This is my entire Dada collection, which contains the following:\n\nDada - Puzzle 1992/2004 *REMASTER* BONUS TRACKS BONUS TRACKS!!! (With music video) 192kbps mp3\nDada - American Highway Flower 1994/2004 *REMASTER* BONUS TRACKS BONUS TRACKS!!! 192kbps mp3\nDada - El Subliminoso 1996/2004 *REMASTER* BONUS TRACKS BONUS TRACKS!!! 192kbps mp3\nDada - Dada 1997 192kbps mp3\nDada - Live: Official Bootleg (Vol. 1) 2003 256kbps mp3 VBR!\nDada - How to be found 2004 192kbps mp3 \nDada - A friend of Pat Robertson 2006 256kbps mp3 VBR!\n\nThe end.\n\nYep, the first three albums are the remaster ones, with the bonus tracks, somewhat of a rarity.\nAll albums are from my personal cd collection exept for Live: Official Bootleg (Vol. 1) and \nA friend of Pat Robertson. Those two were downloaded through amazon... PLEASE DONT HAX MY AMAZONS \n\nAlbum artwork already added to the mp3&amp;#039;s for iTunes users \n\nIf you don&amp;#039;t know who Dada is... wiki it.\n\nI&amp;#039;ll seed for a while, but hopefully when there are more, it will be all up to you guys.\n\nFeel free to steal share mangle claim as your own on different torrent sites.\n\nEnjoy n stuff","torrent":{"xt":"urn:btih:36815060da5cbbd9059ae34441ac98f6162a1a3e","amp;dn":"Dada+COMPLETE%3F+Discography","amp;tr":["udp%3A%2F%2Ftracker.openbittorrent.com%3A80","udp%3A%2F%2Fopen.demonii.com%3A1337","udp%3A%2F%2Ftracker.coppersurfer.tk%3A6969","udp%3A%2F%2Fexodus.desync.com%3A6969"],"infoHash":"36815060da5cbbd9059ae34441ac98f6162a1a3e","infoHashBuffer":{"type":"Buffer","data":[54,129,80,96,218,92,187,217,5,154,227,68,65,172,152,246,22,42,26,62]},"announce":[],"urlList":[]}}