{"title":"WhippedAss--WA-33867 Lorelei Lee, Maitresse Madeline, Mona Lee a","uid":11531269,"size":3049100944,"categoryP":"porn","categoryS":"hd___movies","magnet":"?xt=urn:btih:425571d55b5fc1d647ce51fa9ef3c5c7f93c9d6a&amp;dn=WhippedAss--WA-33867+Lorelei+Lee%2C+Maitresse+Madeline%2C+Mona+Lee+a&amp;tr=udp%3A%2F%2Ftracker.openbittorrent.com%3A80&amp;tr=udp%3A%2F%2Fopen.demonii.com%3A1337&amp;tr=udp%3A%2F%2Ftracker.coppersurfer.tk%3A6969&amp;tr=udp%3A%2F%2Fexodus.desync.com%3A6969","seeders":3,"leechers":1,"uploader":"merzedes","files":-1,"time":1416531088,"description":"Not sure how this can qualify as a 'classic' after only a year, but who are we to judge ? :)\n\nCLASSIC ARCHIVE SHOOT: Czech Whores in HELL: Military Debasement\n\nNov 20, 2014 - Performers: Lorelei Lee ,  Maitresse Madeline ,  Mona Lee  and  Gabrielle Gucci \n\n\nMed, Hi and HD MP4 + Pics.\n\nHD is dupe of previous upload, Med and Hi are new.\n\n\nMaitresse Madeline and Lorelei Lee travel to the Czech Republic to test and recruit slutty slave girls to bring back to the U.S.A. The whores want desperately to escape their arduous lives but it turns out that they don't know the meaning of suffering! Madeline tests their endurance and discipline through a series of military style sex drills. She subjects them to floggers, whips and canes, fucks their asses and pussy's with a strap-on and makes them piss all over themselves in fear. They lick each others filthy cunts and assholes and try to be obedient. The girls even learn some American phrases: &quot;Please&quot;, &quot;Thank you&quot; and &quot;I cum!&quot;\n\nScreens &lt;a href=&quot;\nhttp://www.whippedass.com/site/shoot.jsp?shootId=33867&quot; rel=&quot;nofollow&quot; target=&quot;_NEW&quot;&gt;\nhttp://www.whippedass.com/site/shoot.jsp?shootId=33867&lt;/a&gt;\n\n16 000 Femdom/BDSM/Fetish torrentuploads completed. Man.. feels like every 1000 goes by faster and faster ;)\n\nJust keep on leaving us the nice comments below and we are happy :)\n\n\nAny Questions ?? Read our FAQ!!\n   &lt;a href=&quot;\nhttp://image.bayimg.com/eaea7e9e982a9a677d61e4f5aaf93b7643bd6eeb.jpg&quot; rel=&quot;nofollow&quot; target=&quot;_NEW&quot;&gt;\nhttp://image.bayimg.com/eaea7e9e982a9a677d61e4f5aaf93b7643bd6eeb.jpg&lt;/a&gt;\n\n\nCheers  :-)","torrent":{"xt":"urn:btih:425571d55b5fc1d647ce51fa9ef3c5c7f93c9d6a","amp;dn":"WhippedAss--WA-33867+Lorelei+Lee%2C+Maitresse+Madeline%2C+Mona+Lee+a","amp;tr":["udp%3A%2F%2Ftracker.openbittorrent.com%3A80","udp%3A%2F%2Fopen.demonii.com%3A1337","udp%3A%2F%2Ftracker.coppersurfer.tk%3A6969","udp%3A%2F%2Fexodus.desync.com%3A6969"],"infoHash":"425571d55b5fc1d647ce51fa9ef3c5c7f93c9d6a","infoHashBuffer":{"type":"Buffer","data":[66,85,113,213,91,95,193,214,71,206,81,250,158,243,197,199,249,60,157,106]},"announce":[],"urlList":[]}}