{"title":"BATMAN - THE DARK KNIGHT 017 (2013) (2 covers) (Zone-Empire)","uid":8199691,"size":36874883,"categoryP":"other","categoryS":"comics","magnet":"?xt=urn:btih:4c67904201314e4d62b8f5bd020b204d51f1dcb5&amp;dn=BATMAN+-+THE+DARK+KNIGHT+017+%282013%29+%282+covers%29+%28Zone-Empire%29&amp;tr=udp%3A%2F%2Ftracker.openbittorrent.com%3A80&amp;tr=udp%3A%2F%2Fopen.demonii.com%3A1337&amp;tr=udp%3A%2F%2Ftracker.coppersurfer.tk%3A6969&amp;tr=udp%3A%2F%2Fexodus.desync.com%3A6969","seeders":3,"leechers":0,"uploader":"STFmaryville","files":-1,"time":1361987580,"description":"Ethan Van Sciver's first storyline as regular artist continues as the gory details of The Mad Hatter's past are revealed!\n\nWith The Mad Hatter kidnapping citizens all over Gotham City, not even Batman can figure what he's after.\n\nWritten by: Gregg Hurwitz\nArt by: Ethan Van Sciver\nCover by: Ethan Van Sciver\nVariant Cover by: Ethan Van Sciver\n\nColor, 32 Pages\nOn Sale: Feb 27 2013\n","torrent":{"xt":"urn:btih:4c67904201314e4d62b8f5bd020b204d51f1dcb5","amp;dn":"BATMAN+-+THE+DARK+KNIGHT+017+%282013%29+%282+covers%29+%28Zone-Empire%29","amp;tr":["udp%3A%2F%2Ftracker.openbittorrent.com%3A80","udp%3A%2F%2Fopen.demonii.com%3A1337","udp%3A%2F%2Ftracker.coppersurfer.tk%3A6969","udp%3A%2F%2Fexodus.desync.com%3A6969"],"infoHash":"4c67904201314e4d62b8f5bd020b204d51f1dcb5","infoHashBuffer":{"type":"Buffer","data":[76,103,144,66,1,49,78,77,98,184,245,189,2,11,32,77,81,241,220,181]},"announce":[],"urlList":[]}}