{"title":"Beginner's-Intermediate Guide to BodyBuilding.pdf","uid":9019128,"size":138179,"categoryP":"other","categoryS":"e_books","magnet":"?xt=urn:btih:51803e18196be08a2838e26c8ac53df0e8196338&amp;dn=Beginner%27s-Intermediate+Guide+to+BodyBuilding.pdf&amp;tr=udp%3A%2F%2Ftracker.openbittorrent.com%3A80&amp;tr=udp%3A%2F%2Fopen.demonii.com%3A1337&amp;tr=udp%3A%2F%2Ftracker.coppersurfer.tk%3A6969&amp;tr=udp%3A%2F%2Fexodus.desync.com%3A6969","seeders":4,"leechers":0,"uploader":"sonnie460","files":1,"time":1381258779,"description":"A short ebook writen by me about bodybuilding. This is for beginning to intermediate bodybuilders. Advanced bodybuilders won't find this useful. This brief guide discusses how to build muscle, nutrition, amount of reps, weight to use, and nutrition.","torrent":{"xt":"urn:btih:51803e18196be08a2838e26c8ac53df0e8196338","amp;dn":"Beginner%27s-Intermediate+Guide+to+BodyBuilding.pdf","amp;tr":["udp%3A%2F%2Ftracker.openbittorrent.com%3A80","udp%3A%2F%2Fopen.demonii.com%3A1337","udp%3A%2F%2Ftracker.coppersurfer.tk%3A6969","udp%3A%2F%2Fexodus.desync.com%3A6969"],"infoHash":"51803e18196be08a2838e26c8ac53df0e8196338","infoHashBuffer":{"type":"Buffer","data":[81,128,62,24,25,107,224,138,40,56,226,108,138,197,61,240,232,25,99,56]},"announce":[],"urlList":[]}}