{"title":"Under Your Skin by Sabine Durrant","uid":9679321,"size":716057,"categoryP":"other","categoryS":"e_books","magnet":"?xt=urn:btih:6105058b18c7fa6c826ecd7318945b3c269a9383&amp;dn=Under+Your+Skin+by+Sabine+Durrant&amp;tr=udp%3A%2F%2Ftracker.openbittorrent.com%3A80&amp;tr=udp%3A%2F%2Fopen.demonii.com%3A1337&amp;tr=udp%3A%2F%2Ftracker.coppersurfer.tk%3A6969&amp;tr=udp%3A%2F%2Fexodus.desync.com%3A6969","seeders":4,"leechers":2,"uploader":"PirateBook","files":1,"time":1393633250,"description":"\nGaby Mortimer is the woman who has it all. But everything changes when she finds a body on the common near her home. She\u0019s shaken and haunted by the image of the lifeless young woman, and frightened that the killer, still at large, could strike again.\n\nBefore long, the police have a lead. The evidence points to a very clear suspect. One Gaby never saw coming . . .\n\nFull of twists and turns, this is a dark and suspenseful psychological thriller that will make you secondguess everything. Because you can never be too sure about anything, especially when it comes to murder.\n\nGenre: Mystery/Thriller","torrent":{"xt":"urn:btih:6105058b18c7fa6c826ecd7318945b3c269a9383","amp;dn":"Under+Your+Skin+by+Sabine+Durrant","amp;tr":["udp%3A%2F%2Ftracker.openbittorrent.com%3A80","udp%3A%2F%2Fopen.demonii.com%3A1337","udp%3A%2F%2Ftracker.coppersurfer.tk%3A6969","udp%3A%2F%2Fexodus.desync.com%3A6969"],"infoHash":"6105058b18c7fa6c826ecd7318945b3c269a9383","infoHashBuffer":{"type":"Buffer","data":[97,5,5,139,24,199,250,108,130,110,205,115,24,148,91,60,38,154,147,131]},"announce":[],"urlList":[]}}