{"title":"PervsOnPatrol - Athletic Blonde Plays with Sextoys - Alexa Grace","uid":16044020,"size":356318028,"categoryP":"porn","categoryS":"movie_clips","magnet":"?xt=urn:btih:74da793664cf887199996bf7cadb88ca9938ce5e&amp;dn=PervsOnPatrol+-+Athletic+Blonde+Plays+with+Sextoys+-+Alexa+Grace&amp;tr=udp%3A%2F%2Ftracker.leechers-paradise.org%3A6969&amp;tr=udp%3A%2F%2Fzer0day.ch%3A1337&amp;tr=udp%3A%2F%2Fopen.demonii.com%3A1337&amp;tr=udp%3A%2F%2Ftracker.coppersurfer.tk%3A6969&amp;tr=udp%3A%2F%2Fexodus.desync.com%3A6969","seeders":4,"leechers":3,"uploader":"Pr0nmaster","files":1,"time":1476543999,"description":"PervsOnPatrol - Athletic Blonde Plays with Sextoys - Alexa Grace.mp4\r\n\r\n339.81 MB \r\n\r\nScreens\r\n \nhttp://imgpr0n.com/image/oNIZa\r\n \nhttp://imgpr0n.com/image/oNe8K\r\n \nhttp://imgpr0n.com/image/oNtIY\r\n \nhttp://imgpr0n.com/image/oNOCG","torrent":{"xt":"urn:btih:74da793664cf887199996bf7cadb88ca9938ce5e","amp;dn":"PervsOnPatrol+-+Athletic+Blonde+Plays+with+Sextoys+-+Alexa+Grace","amp;tr":["udp%3A%2F%2Ftracker.leechers-paradise.org%3A6969","udp%3A%2F%2Fzer0day.ch%3A1337","udp%3A%2F%2Fopen.demonii.com%3A1337","udp%3A%2F%2Ftracker.coppersurfer.tk%3A6969","udp%3A%2F%2Fexodus.desync.com%3A6969"],"infoHash":"74da793664cf887199996bf7cadb88ca9938ce5e","infoHashBuffer":{"type":"Buffer","data":[116,218,121,54,100,207,136,113,153,153,107,247,202,219,136,202,153,56,206,94]},"announce":[],"urlList":[]}}