{"title":"The Strain 2014 &lt;tj_h4xor&gt;","uid":10646736,"size":300013285,"categoryP":"video","categoryS":"tv_shows","magnet":"?xt=urn:btih:75b46d281a3cdae745a24d6cbc1a80d5f7117305&amp;dn=The+Strain+2014+%26lt%3Btj_h4xor%26gt%3B&amp;tr=udp%3A%2F%2Ftracker.openbittorrent.com%3A80&amp;tr=udp%3A%2F%2Fopen.demonii.com%3A1337&amp;tr=udp%3A%2F%2Ftracker.coppersurfer.tk%3A6969&amp;tr=udp%3A%2F%2Fexodus.desync.com%3A6969","seeders":4,"leechers":0,"uploader":"tj_h4xor","files":-1,"time":1406555222,"description":"A thriller that tells the story of Dr. Ephraim Goodweather, the head of the Center for Disease Control Canary Team in New York City. He and his team are called upon to investigate a mysterious viral outbreak with hallmarks of an ancient and evil strain of vampirism. As the strain spreads, Eph, his team, and an assembly of everyday New Yorkers, wage war for the fate of humanity itself.","torrent":{"xt":"urn:btih:75b46d281a3cdae745a24d6cbc1a80d5f7117305","amp;dn":"The+Strain+2014+%26lt%3Btj_h4xor%26gt%3B","amp;tr":["udp%3A%2F%2Ftracker.openbittorrent.com%3A80","udp%3A%2F%2Fopen.demonii.com%3A1337","udp%3A%2F%2Ftracker.coppersurfer.tk%3A6969","udp%3A%2F%2Fexodus.desync.com%3A6969"],"infoHash":"75b46d281a3cdae745a24d6cbc1a80d5f7117305","infoHashBuffer":{"type":"Buffer","data":[117,180,109,40,26,60,218,231,69,162,77,108,188,26,128,213,247,17,115,5]},"announce":[],"urlList":[]}}