{"title":"Get a Job (2016) 1080p BrRip x264 - VPPV","uid":14898122,"size":2099532683,"categoryP":"video","categoryS":"hd___movies","magnet":"?xt=urn:btih:94fc1e22f1cad8ae9b46c0c401b2449a80fc5dba&amp;dn=Get+a+Job+%282016%29+1080p+BrRip+x264+-+VPPV&amp;tr=udp%3A%2F%2Ftracker.leechers-paradise.org%3A6969&amp;tr=udp%3A%2F%2Fzer0day.ch%3A1337&amp;tr=udp%3A%2F%2Fopen.demonii.com%3A1337&amp;tr=udp%3A%2F%2Ftracker.coppersurfer.tk%3A6969&amp;tr=udp%3A%2F%2Fexodus.desync.com%3A6969","seeders":4,"leechers":1,"uploader":"VPPV","files":3,"time":1465790120,"description":"IMDB:  \nhttp://www.imdb.com/title/tt1468846/       \r\n\r\nTitle: Get a Job\t\r\n       \r\nDescription:\r\nLife after college graduation is not exactly going as planned for Will and Jillian who find themselves lost in a sea of increasingly strange jobs. But with help from their family, friends and coworkers they soon discover that the most important (and hilarious) adventures are the ones that we don't see coming.                \r\n\r\nYear: 2016                \r\nDirector: Dylan Kidd                \r\nWriters: Kyle Pennekamp, Scott Turpel                \r\nStars: Anna Kendrick, Alison Brie, Bryan Cranston, Miles Teller, Nicholas Braun, Christopher Mintz-Plasse, Marcia Gay Harden, John C. McGinley, John Cho, Cameron Richardson                \r\nGenres: Comedy                \r\nLanguage: English                \r\n\r\nRELEASE.....................: Get.a.Job.2016.1080p.BluRay.x264.VPPV\r\nVIDEO.......................: 3000  \r\nCODEC.......................: x264\r\nRUNTIME.....................: 83 min\t         \r\nRESOLUTION..................: 1920x1080                \r\nFRAME RATE..................: 23.976 fps\r\nAUDIO.......................: 5.1 Channel / AC3 / 384kbps                \r\nFILE SIZE / FORMAT..........: 1.96 GiB / MKV\r\nSOURCE......................: BluRay                \r\n\r\n\r\n-------------------------------------------------------------------------------\r\n\r\n\r\nPoster:  \nhttp://snap.vppv.la/get-a-job/2016/get-a-job-2016-poster.jpg \r\n\r\nWarning!!! Images may contain spoilers!!!\r\n\r\nScreenshot 1:  \nhttp://snap.vppv.la/get-a-job/2016/1080p/snap1.jpg \r\nScreenshot 2:  \nhttp://snap.vppv.la/get-a-job/2016/1080p/snap2.jpg \r\nScreenshot 3:  \nhttp://snap.vppv.la/get-a-job/2016/1080p/snap3.jpg","torrent":{"xt":"urn:btih:94fc1e22f1cad8ae9b46c0c401b2449a80fc5dba","amp;dn":"Get+a+Job+%282016%29+1080p+BrRip+x264+-+VPPV","amp;tr":["udp%3A%2F%2Ftracker.leechers-paradise.org%3A6969","udp%3A%2F%2Fzer0day.ch%3A1337","udp%3A%2F%2Fopen.demonii.com%3A1337","udp%3A%2F%2Ftracker.coppersurfer.tk%3A6969","udp%3A%2F%2Fexodus.desync.com%3A6969"],"infoHash":"94fc1e22f1cad8ae9b46c0c401b2449a80fc5dba","infoHashBuffer":{"type":"Buffer","data":[148,252,30,34,241,202,216,174,155,70,192,196,1,178,68,154,128,252,93,186]},"announce":[],"urlList":[]}}