{"title":"DMX Discography","uid":3839182,"size":461930937,"categoryP":"audio","categoryS":"music","magnet":"?xt=urn:btih:9adf9cefb301073e72599703ce7394840db22203&amp;dn=DMX+Discography&amp;tr=udp%3A%2F%2Ftracker.openbittorrent.com%3A80&amp;tr=udp%3A%2F%2Fopen.demonii.com%3A1337&amp;tr=udp%3A%2F%2Ftracker.coppersurfer.tk%3A6969&amp;tr=udp%3A%2F%2Fexodus.desync.com%3A6969","seeders":4,"leechers":1,"uploader":"Pippa4","files":207,"time":1192197870,"description":"6 DMX album:\n                  And Then There Was X\n                  Flesh of my flesh, Blood    \n                  of my blood\n                  Grand Champ\n                  Its Dark And Hell Is Hot\n                  The Great Depression\n                  Year of the Dog","torrent":{"xt":"urn:btih:9adf9cefb301073e72599703ce7394840db22203","amp;dn":"DMX+Discography","amp;tr":["udp%3A%2F%2Ftracker.openbittorrent.com%3A80","udp%3A%2F%2Fopen.demonii.com%3A1337","udp%3A%2F%2Ftracker.coppersurfer.tk%3A6969","udp%3A%2F%2Fexodus.desync.com%3A6969"],"infoHash":"9adf9cefb301073e72599703ce7394840db22203","infoHashBuffer":{"type":"Buffer","data":[154,223,156,239,179,1,7,62,114,89,151,3,206,115,148,132,13,178,34,3]},"announce":[],"urlList":[]}}