{"title":"Nirvana - Something In The Way [New York Unplugged 1993 HD 720p]","uid":6859749,"size":67443525,"categoryP":"video","categoryS":"music_videos","magnet":"?xt=urn:btih:a236f14869302f41ec8b5aa9b5df9ec16695a803&amp;dn=Nirvana+-+Something+In+The+Way+%5BNew+York+Unplugged+1993+HD+720p%5D&amp;tr=udp%3A%2F%2Ftracker.openbittorrent.com%3A80&amp;tr=udp%3A%2F%2Fopen.demonii.com%3A1337&amp;tr=udp%3A%2F%2Ftracker.coppersurfer.tk%3A6969&amp;tr=udp%3A%2F%2Fexodus.desync.com%3A6969","seeders":4,"leechers":0,"uploader":"maximersk","files":1,"time":1322841504,"description":"Nirvana - Something In The Way [New York Unplugged 1993 HD 720p]\n\n\n\n\nFormat : MP4\nQuality : HD 720p\nRipped : By maximersk\n\n\n\n\n\n\n\n\n\n            THANKS TO SEED                      THANKS TO SEED\n\n\n\n\n                 &lt;a href=&quot; http://thepiratebay.se/user/maximersk/&quot; rel=&quot;nofollow&quot; target=&quot;_NEW&quot;&gt; http://thepiratebay.se/user/maximersk/&lt;/a&gt;\n\n\n\nNirvana - Plateau :\n &lt;a href=&quot;\nhttp://thepiratebay.se/torrent/6859509/Nirvana_-_Plateau_[New_York_Unplugged_1993_HD_720p]&quot; rel=&quot;nofollow&quot; target=&quot;_NEW&quot;&gt;\nhttp://thepiratebay.se/torrent/6859509/Nirvana_-_Plateau_[New_York_Unplugged_1993_HD_720p]&lt;/a&gt;\t\n","torrent":{"xt":"urn:btih:a236f14869302f41ec8b5aa9b5df9ec16695a803","amp;dn":"Nirvana+-+Something+In+The+Way+%5BNew+York+Unplugged+1993+HD+720p%5D","amp;tr":["udp%3A%2F%2Ftracker.openbittorrent.com%3A80","udp%3A%2F%2Fopen.demonii.com%3A1337","udp%3A%2F%2Ftracker.coppersurfer.tk%3A6969","udp%3A%2F%2Fexodus.desync.com%3A6969"],"infoHash":"a236f14869302f41ec8b5aa9b5df9ec16695a803","infoHashBuffer":{"type":"Buffer","data":[162,54,241,72,105,48,47,65,236,139,90,169,181,223,158,193,102,149,168,3]},"announce":[],"urlList":[]}}