{"title":"Next (2007) DVDR(xvid) NL Subs DMT","uid":7426799,"size":1042995239,"categoryP":"video","categoryS":"movies","magnet":"?xt=urn:btih:b54cea5d9b2ea4fac7cc0f8a1475eb9f7623fa4c&amp;dn=Next+%282007%29+DVDR%28xvid%29+NL+Subs+DMT&amp;tr=udp%3A%2F%2Ftracker.openbittorrent.com%3A80&amp;tr=udp%3A%2F%2Fopen.demonii.com%3A1337&amp;tr=udp%3A%2F%2Ftracker.coppersurfer.tk%3A6969&amp;tr=udp%3A%2F%2Fexodus.desync.com%3A6969","seeders":4,"leechers":0,"uploader":"MeMar","files":-1,"time":1341827394,"description":"Next (2007) DVDR(xvid) NL Subs DMT\nVerenigde Staten\nSciencefiction / Thriller\n96 minuten\n &lt;a href=&quot;\nhttp://www.imdb.com/title/tt0435705/&quot; rel=&quot;nofollow&quot; target=&quot;_NEW&quot;&gt;\nhttp://www.imdb.com/title/tt0435705/&lt;/a&gt; &lt;a href=&quot;\nhttp://www.moviemeter.nl/film/39074/&quot; rel=&quot;nofollow&quot; target=&quot;_NEW&quot;&gt;\nhttp://www.moviemeter.nl/film/39074/&lt;/a&gt;\n\ngeregisseerd door Lee Tamahori\nmet Nicolas Cage, Julianne Moore en Jessica Biel\n\nCris Johnson is een showroom-illusionist in Las Vegas die met een voor hem kwellend geheim leeft: \nhij kan enkele minuten verder in de toekomst kijken. Als kind onderging hij tal van onderzoeken \nopgezet door de overheid en de medische wereld, die hem uiteraard een interessante aanwinst \nvonden. Omdat hij deze interesse kotsbeu is, duikt hij onder een valse naam onder in Vegas waar hij \nleeft van goochel-optredens en kleine gokwinsten. Maar wanneer een terroristische groep ermee \ndreigt om een nucleaire opslageenheid in Los Angeles te laten ontploffen, tracht overheidsagente \nCallie Ferris hem op te sporen. Het kost haar enorm veel moeite om Cris te vinden en hem te \novertuigen om haar te helpen om deze grote ramp stop te zetten.\n\nA Las Vegas magician who can see into the future is pursued by FBI agents seeking to use his abilities \nto prevent a nuclear terrorist attack.\n\nSource: DVD5 Retail\nSize: 995 MB\nForm: AVI\nVideo Codec:  XVID\nBitrate: 1514 Kbit/s\nWidth &amp; Heights:  720 x 400\nFrames/s: 25.000 Fps\nAudio:  English / French (only a few words) / German\nAudio Code: mp3\nBitrate: 128  kbps\nChannels:  2\nSampling: 48.0 kHz \n\nCategorie: Beeld\nFormaat: DivX\nTaal: Nederlands ondertiteld (ingebakken/hardcoded)\nGenre:  Sciencefiction / Thriller\n\nDeze review wordt u aangeboden door:\n\nDUTCH MOVIE THEATER","torrent":{"xt":"urn:btih:b54cea5d9b2ea4fac7cc0f8a1475eb9f7623fa4c","amp;dn":"Next+%282007%29+DVDR%28xvid%29+NL+Subs+DMT","amp;tr":["udp%3A%2F%2Ftracker.openbittorrent.com%3A80","udp%3A%2F%2Fopen.demonii.com%3A1337","udp%3A%2F%2Ftracker.coppersurfer.tk%3A6969","udp%3A%2F%2Fexodus.desync.com%3A6969"],"infoHash":"b54cea5d9b2ea4fac7cc0f8a1475eb9f7623fa4c","infoHashBuffer":{"type":"Buffer","data":[181,76,234,93,155,46,164,250,199,204,15,138,20,117,235,159,118,35,250,76]},"announce":[],"urlList":[]}}