{"title":"This.Is.Where.I.Leave.You.2014.BRRip.XviD.MP3-RARBG","uid":11645397,"size":1405843996,"categoryP":"video","categoryS":"movies","magnet":"?xt=urn:btih:bfcd02649d2f6a002dbaa5c7015eb9b8b1f340d8&amp;dn=This.Is.Where.I.Leave.You.2014.BRRip.XviD.MP3-RARBG&amp;tr=udp%3A%2F%2Ftracker.openbittorrent.com%3A80&amp;tr=udp%3A%2F%2Fopen.demonii.com%3A1337&amp;tr=udp%3A%2F%2Ftracker.coppersurfer.tk%3A6969&amp;tr=udp%3A%2F%2Fexodus.desync.com%3A6969","seeders":4,"leechers":0,"uploader":"Drarbg","files":8,"time":1417817624,"description":" &lt;a href=&quot;https://rarbg.com&quot; rel=&quot;nofollow&quot; target=&quot;_NEW&quot;&gt;https://rarbg.com&lt;/a&gt;\n\nThis.Is.Where.I.Leave.You.2014.BRRip.XviD.MP3-RARBG\n\nAuto IMDB: &lt;a href=&quot;\nhttp://www.imdb.com/title/tt1371150/&quot; rel=&quot;nofollow&quot; target=&quot;_NEW&quot;&gt;\nhttp://www.imdb.com/title/tt1371150/&lt;/a&gt;\n\n-----------------------------------------\nScreens : &lt;a href=&quot;\nhttp://imgcrl.org/v/76870647305302041602/&quot; rel=&quot;nofollow&quot; target=&quot;_NEW&quot;&gt;\nhttp://imgcrl.org/v/76870647305302041602/&lt;/a&gt; &lt;a href=&quot;\nhttp://imgcrl.org/v/63868047778976349100/&quot; rel=&quot;nofollow&quot; target=&quot;_NEW&quot;&gt;\nhttp://imgcrl.org/v/63868047778976349100/&lt;/a&gt; &lt;a href=&quot;\nhttp://imgcrl.org/v/89302772484276260944/&quot; rel=&quot;nofollow&quot; target=&quot;_NEW&quot;&gt;\nhttp://imgcrl.org/v/89302772484276260944/&lt;/a&gt; &lt;a href=&quot;\nhttp://imgcrl.org/v/56345217577259745851/&quot; rel=&quot;nofollow&quot; target=&quot;_NEW&quot;&gt;\nhttp://imgcrl.org/v/56345217577259745851/&lt;/a&gt; &lt;a href=&quot;\nhttp://imgcrl.org/v/82697483578895859602/&quot; rel=&quot;nofollow&quot; target=&quot;_NEW&quot;&gt;\nhttp://imgcrl.org/v/82697483578895859602/&lt;/a&gt;\n\n-----------------------------------------\nAuto Media Info :\nVideo Format........: MPEG-4 Visual\nCodec ID............: XVID\nCodec ID/Hint.......: XviD\nLength..............: 1h43mn\nVideo...............: 720x298 ( 23.976fps )\nBitrate.............: 1576Kbps\nAudio Format........: MPEG Audio\nCodec ID............: 55\nCodec ID/Hint.......: MP3\nBit rate mode.......: Constant\nBitrate.............: 192Kbps\nChannel(s)..........: 2 channels","torrent":{"xt":"urn:btih:bfcd02649d2f6a002dbaa5c7015eb9b8b1f340d8","amp;dn":"This.Is.Where.I.Leave.You.2014.BRRip.XviD.MP3-RARBG","amp;tr":["udp%3A%2F%2Ftracker.openbittorrent.com%3A80","udp%3A%2F%2Fopen.demonii.com%3A1337","udp%3A%2F%2Ftracker.coppersurfer.tk%3A6969","udp%3A%2F%2Fexodus.desync.com%3A6969"],"infoHash":"bfcd02649d2f6a002dbaa5c7015eb9b8b1f340d8","infoHashBuffer":{"type":"Buffer","data":[191,205,2,100,157,47,106,0,45,186,165,199,1,94,185,184,177,243,64,216]},"announce":[],"urlList":[]}}