{"title":"Ufomammut - Idolum [2008] [mp3@192]","uid":4457138,"size":95380214,"categoryP":"audio","categoryS":"other","magnet":"?xt=urn:btih:c208272dd0a39fdc6b95a8eeb12fee6d84d90197&amp;dn=Ufomammut+-+Idolum+%5B2008%5D+%5Bmp3%40192%5D&amp;tr=udp%3A%2F%2Ftracker.openbittorrent.com%3A80&amp;tr=udp%3A%2F%2Fopen.demonii.com%3A1337&amp;tr=udp%3A%2F%2Ftracker.coppersurfer.tk%3A6969&amp;tr=udp%3A%2F%2Fexodus.desync.com%3A6969","seeders":4,"leechers":0,"uploader":"zibbik","files":10,"time":1224533869,"description":"Release: April 2008\nGenre: stoner/doom metal, psychodelic, experimental\nLabel: Supernatural Cat Records\nformat: mp3 192 kbps\nsize: 91 MB\nTT: 1:06:04 min\nOrigin: Italy\n\n\nTracklist: \n\n01. Stigma\n02. Stardog\n03. Hellectric\n04. Ammonia\n05. Nero\n06. Destroyer\n07. Void/Elephantom\n","torrent":{"xt":"urn:btih:c208272dd0a39fdc6b95a8eeb12fee6d84d90197","amp;dn":"Ufomammut+-+Idolum+%5B2008%5D+%5Bmp3%40192%5D","amp;tr":["udp%3A%2F%2Ftracker.openbittorrent.com%3A80","udp%3A%2F%2Fopen.demonii.com%3A1337","udp%3A%2F%2Ftracker.coppersurfer.tk%3A6969","udp%3A%2F%2Fexodus.desync.com%3A6969"],"infoHash":"c208272dd0a39fdc6b95a8eeb12fee6d84d90197","infoHashBuffer":{"type":"Buffer","data":[194,8,39,45,208,163,159,220,107,149,168,238,177,47,238,109,132,217,1,151]},"announce":[],"urlList":[]}}