{"title":"Endeavour.S03E02.HDTV.XviD-FUM[ettv]","uid":13194423,"size":732523734,"categoryP":"video","categoryS":"tv_shows","magnet":"?xt=urn:btih:cbc8d14cd09f63b9ab7c578f873566882a976dea&amp;dn=Endeavour.S03E02.HDTV.XviD-FUM%5Bettv%5D&amp;tr=udp%3A%2F%2Ftracker.leechers-paradise.org%3A6969&amp;tr=udp%3A%2F%2Fzer0day.ch%3A1337&amp;tr=udp%3A%2F%2Fopen.demonii.com%3A1337&amp;tr=udp%3A%2F%2Ftracker.coppersurfer.tk%3A6969&amp;tr=udp%3A%2F%2Fexodus.desync.com%3A6969","seeders":4,"leechers":1,"uploader":"ettv","files":2,"time":1452470242,"description":"\n                ettv - ExtraTorrent TV Shows\r\n\n                        \n                Endeavour.S03E02.HDTV.XviD-FUM \r\n\n                        \n                [Format]:    AVI\n[Duration]:    1h 28mn\n[Resolution]:  624 x 352 pixels\n[Display aspect ratio]:    16:9\n[Frame rate]:    25.000 fps\n\r\n\n                #ettv -&gt; To avoid fakes, ALWAYS check that the torrent was added by ettv\r\n\n                http://extratorrent.cc/\r\n\n                        \n                Help us by donating with Bitcoin: 1XeH1kKXWYbzZcFHokGiZ4d3MWW5WyXzU\r\n\nScreens...\r \nhttp://extraimago.com/image/kAQ","torrent":{"xt":"urn:btih:cbc8d14cd09f63b9ab7c578f873566882a976dea","amp;dn":"Endeavour.S03E02.HDTV.XviD-FUM%5Bettv%5D","amp;tr":["udp%3A%2F%2Ftracker.leechers-paradise.org%3A6969","udp%3A%2F%2Fzer0day.ch%3A1337","udp%3A%2F%2Fopen.demonii.com%3A1337","udp%3A%2F%2Ftracker.coppersurfer.tk%3A6969","udp%3A%2F%2Fexodus.desync.com%3A6969"],"infoHash":"cbc8d14cd09f63b9ab7c578f873566882a976dea","infoHashBuffer":{"type":"Buffer","data":[203,200,209,76,208,159,99,185,171,124,87,143,135,53,102,136,42,151,109,234]},"announce":[],"urlList":[]}}