{"title":"Monsters.University.2013.720p.BluRay.x264-SPARKS","uid":9047748,"size":3571084409,"categoryP":"video","categoryS":"hd___movies","magnet":"?xt=urn:btih:dca36f6f1d785408e2e66b4edbb049d5acf7d209&amp;dn=Monsters.University.2013.720p.BluRay.x264-SPARKS&amp;tr=udp%3A%2F%2Ftracker.openbittorrent.com%3A80&amp;tr=udp%3A%2F%2Fopen.demonii.com%3A1337&amp;tr=udp%3A%2F%2Ftracker.coppersurfer.tk%3A6969&amp;tr=udp%3A%2F%2Fexodus.desync.com%3A6969","seeders":4,"leechers":1,"uploader":"UltraTorrents","files":5,"time":1381794027,"description":"INFO, POSTER &amp; TRAILER\n                                                                                       &lt;a href=&quot;\nhttp://www.sharepixon.net/movies/monsters-university&quot; rel=&quot;nofollow&quot; target=&quot;_NEW&quot;&gt;\nhttp://www.sharepixon.net/movies/monsters-university&lt;/a&gt;\n\n[url]http://www.sharepixon.net/movies/monsters-university[/url]\n\n\nSCREENSHOTS:\n                                                                                      &lt;a href=&quot;\nhttp://img.sharepixon.net/?v=monstewzw.png&quot; rel=&quot;nofollow&quot; target=&quot;_NEW&quot;&gt;\nhttp://img.sharepixon.net/?v=monstewzw.png&lt;/a&gt;   &lt;a href=&quot;\nhttp://img.sharepixon.net/?v=monsteyly.png&quot; rel=&quot;nofollow&quot; target=&quot;_NEW&quot;&gt;\nhttp://img.sharepixon.net/?v=monsteyly.png&lt;/a&gt;\n\n[url]http://img.sharepixon.net/?v=monstewzw.png[/url]\t\n[url]http://img.sharepixon.net/?v=monsteyly.png[/url]\t\n\t","torrent":{"xt":"urn:btih:dca36f6f1d785408e2e66b4edbb049d5acf7d209","amp;dn":"Monsters.University.2013.720p.BluRay.x264-SPARKS","amp;tr":["udp%3A%2F%2Ftracker.openbittorrent.com%3A80","udp%3A%2F%2Fopen.demonii.com%3A1337","udp%3A%2F%2Ftracker.coppersurfer.tk%3A6969","udp%3A%2F%2Fexodus.desync.com%3A6969"],"infoHash":"dca36f6f1d785408e2e66b4edbb049d5acf7d209","infoHashBuffer":{"type":"Buffer","data":[220,163,111,111,29,120,84,8,226,230,107,78,219,176,73,213,172,247,210,9]},"announce":[],"urlList":[]}}