{"title":"La Dieta Definitiva - Alberto Sedler","uid":5565176,"size":22910440,"categoryP":"other","categoryS":"e_books","magnet":"?xt=urn:btih:dd437fa87891f65a3e40a6d33738f81a86693e76&amp;dn=La+Dieta+Definitiva+-+Alberto+Sedler&amp;tr=udp%3A%2F%2Ftracker.openbittorrent.com%3A80&amp;tr=udp%3A%2F%2Fopen.demonii.com%3A1337&amp;tr=udp%3A%2F%2Ftracker.coppersurfer.tk%3A6969&amp;tr=udp%3A%2F%2Fexodus.desync.com%3A6969","seeders":4,"leechers":0,"uploader":"chusca","files":5,"time":1273959560,"description":"Ã‚Â¿CÃƒÂ³mo quemar las grasas del cuerpo, perder peso, y obtener un cuerpo ideal fÃƒÂ¡cilmente y permanentemente incluso si te sientas en tu escritorio, frente a la computadora o en el sofÃƒÂ¡ todo el dÃƒÂ­a? Ã‚Â¿Y si perder peso llegarÃƒÂ¡ a ser tan simple que todo lo que tendrÃƒÂ­as que hacer serÃƒÂ­a sentarte en tu escritorio, computadora o sofÃƒÂ¡ todo el dÃƒÂ­a y perder peso automÃƒÂ¡ticamente sin el uso de pÃƒÂ­ldoras dietÃƒÂ©ticas y sin jamÃƒÂ¡s poner un pie en el gimnasio? EntÃƒÂ©rate cÃƒÂ³mo con el nuevo libro innovador, PÃƒÂ©rdida de peso, La Dieta Definitiva. ","torrent":{"xt":"urn:btih:dd437fa87891f65a3e40a6d33738f81a86693e76","amp;dn":"La+Dieta+Definitiva+-+Alberto+Sedler","amp;tr":["udp%3A%2F%2Ftracker.openbittorrent.com%3A80","udp%3A%2F%2Fopen.demonii.com%3A1337","udp%3A%2F%2Ftracker.coppersurfer.tk%3A6969","udp%3A%2F%2Fexodus.desync.com%3A6969"],"infoHash":"dd437fa87891f65a3e40a6d33738f81a86693e76","infoHashBuffer":{"type":"Buffer","data":[221,67,127,168,120,145,246,90,62,64,166,211,55,56,248,26,134,105,62,118]},"announce":[],"urlList":[]}}