{"title":"Games in the Dark EP (2008)","uid":11186924,"size":25325817,"categoryP":"audio","categoryS":"music","magnet":"?xt=urn:btih:f19806bb6c5e6b4a9f7e590399a324b53042bc5d&amp;dn=Games+in+the+Dark+EP+%282008%29&amp;tr=udp%3A%2F%2Ftracker.openbittorrent.com%3A80&amp;tr=udp%3A%2F%2Fopen.demonii.com%3A1337&amp;tr=udp%3A%2F%2Ftracker.coppersurfer.tk%3A6969&amp;tr=udp%3A%2F%2Fexodus.desync.com%3A6969","seeders":4,"leechers":1,"uploader":"belthagor","files":5,"time":1412934240,"description":"Ben Howard - [Games In The Dark #01] Games In The Dark [4:50]\nBen Howard - [Games In The Dark #02] Are You Ready [5:25]\nBen Howard - [Games In The Dark #03] Empty Corridors [5:14]\nBen Howard - [Games In The Dark #04] Wouldnt Be A Lie [4:22]\nBen Howard - [Games In The Dark #05] Keep Your Head Up [6:26]","torrent":{"xt":"urn:btih:f19806bb6c5e6b4a9f7e590399a324b53042bc5d","amp;dn":"Games+in+the+Dark+EP+%282008%29","amp;tr":["udp%3A%2F%2Ftracker.openbittorrent.com%3A80","udp%3A%2F%2Fopen.demonii.com%3A1337","udp%3A%2F%2Ftracker.coppersurfer.tk%3A6969","udp%3A%2F%2Fexodus.desync.com%3A6969"],"infoHash":"f19806bb6c5e6b4a9f7e590399a324b53042bc5d","infoHashBuffer":{"type":"Buffer","data":[241,152,6,187,108,94,107,74,159,126,89,3,153,163,36,181,48,66,188,93]},"announce":[],"urlList":[]}}