{"title":"Big Tit Creampie 33 XXX DVDRip x264-RedSecTioN","uid":11888601,"size":2338462027,"categoryP":"porn","categoryS":"movies","magnet":"?xt=urn:btih:f7e53e69dea836ddcf1a5563354a547da33b8673&amp;dn=Big+Tit+Creampie+33+XXX+DVDRip+x264-RedSecTioN&amp;tr=udp%3A%2F%2Ftracker.openbittorrent.com%3A80&amp;tr=udp%3A%2F%2Fopen.demonii.com%3A1337&amp;tr=udp%3A%2F%2Ftracker.coppersurfer.tk%3A6969&amp;tr=udp%3A%2F%2Fexodus.desync.com%3A6969","seeders":4,"leechers":1,"uploader":"xxxlavalxxx","files":7,"time":1430921122,"description":"Categories Big Boobs, Cream Pie, Cumshots, Gonzo\n\nCast Brooklyn Chase, Peta Jensen, Destiny Dixon, Jasmine Jae, Charisma Cappelli\n\nBrooklyn Chase - She earns her reward of cum in her pussy!Charisma Capelli - Big tit blonde fucked in the ass and creampied!!Jasmin Jae - Hot British babe pussy creampie from a shy guy!Peta Jensen - Peta's creampie craze!Destiny Dixon - Big tit blonde begs for the creampie!\n &lt;a href=&quot;\nhttp://imgdone.com/viewer.php?file=64905599466706677715.jpg&quot; rel=&quot;nofollow&quot; target=&quot;_NEW&quot;&gt;\nhttp://imgdone.com/viewer.php?file=64905599466706677715.jpg&lt;/a&gt;\n    \t &lt;a href=&quot;\nhttp://imgdone.com/viewer.php?file=32485961202291730878.jpg&quot; rel=&quot;nofollow&quot; target=&quot;_NEW&quot;&gt;\nhttp://imgdone.com/viewer.php?file=32485961202291730878.jpg&lt;/a&gt;\n    \t &lt;a href=&quot;\nhttp://imgdone.com/viewer.php?file=89982880590070255182.jpeg&quot; rel=&quot;nofollow&quot; target=&quot;_NEW&quot;&gt;\nhttp://imgdone.com/viewer.php?file=89982880590070255182.jpeg&lt;/a&gt;","torrent":{"xt":"urn:btih:f7e53e69dea836ddcf1a5563354a547da33b8673","amp;dn":"Big+Tit+Creampie+33+XXX+DVDRip+x264-RedSecTioN","amp;tr":["udp%3A%2F%2Ftracker.openbittorrent.com%3A80","udp%3A%2F%2Fopen.demonii.com%3A1337","udp%3A%2F%2Ftracker.coppersurfer.tk%3A6969","udp%3A%2F%2Fexodus.desync.com%3A6969"],"infoHash":"f7e53e69dea836ddcf1a5563354a547da33b8673","infoHashBuffer":{"type":"Buffer","data":[247,229,62,105,222,168,54,221,207,26,85,99,53,74,84,125,163,59,134,115]},"announce":[],"urlList":[]}}