{"title":"Stone Sour - Come What(ever) May","uid":3551955,"size":83559323,"categoryP":"audio","categoryS":"music","magnet":"?xt=urn:btih:fc8481d844210f0ff30248794d91fce0b359e2d0&amp;dn=Stone+Sour+-+Come+What%28ever%29+May&amp;tr=udp%3A%2F%2Ftracker.openbittorrent.com%3A80&amp;tr=udp%3A%2F%2Fopen.demonii.com%3A1337&amp;tr=udp%3A%2F%2Ftracker.coppersurfer.tk%3A6969&amp;tr=udp%3A%2F%2Fexodus.desync.com%3A6969","seeders":4,"leechers":0,"uploader":"Snowboarder1980","files":18,"time":1162755616,"description":"Come What(ever) May [2006] \n\n01. 30/30-150\n02. Come What(ever) May\n03. Hell &amp; Consequences\n04. Sillyworld\n05. Made Of Scars\n06. Reborn\n07. Your God\n08. Through Glass\n09. Socio\n10. 1st Person\n11. Cardiff\n12. Zzyxz Road\n","torrent":{"xt":"urn:btih:fc8481d844210f0ff30248794d91fce0b359e2d0","amp;dn":"Stone+Sour+-+Come+What%28ever%29+May","amp;tr":["udp%3A%2F%2Ftracker.openbittorrent.com%3A80","udp%3A%2F%2Fopen.demonii.com%3A1337","udp%3A%2F%2Ftracker.coppersurfer.tk%3A6969","udp%3A%2F%2Fexodus.desync.com%3A6969"],"infoHash":"fc8481d844210f0ff30248794d91fce0b359e2d0","infoHashBuffer":{"type":"Buffer","data":[252,132,129,216,68,33,15,15,243,2,72,121,77,145,252,224,179,89,226,208]},"announce":[],"urlList":[]}}